pyeos_client/EOSChainApi.py
pyeos_client/EOSWalletApi.py
pyeos_client/NodeosConnect.py
pyeos_client/__init__.py
pyeos_client-0.1.9.dist-info/METADATA
pyeos_client-0.1.9.dist-info/RECORD
pyeos_client-0.1.9.dist-info/WHEEL
pyeos_client-0.1.9.dist-info/top_level.txt
